django_logit/__init__.py
django_logit/djlogit.py
django_logit-1.1.4.dist-info/METADATA
django_logit-1.1.4.dist-info/WHEEL
django_logit-1.1.4.dist-info/top_level.txt
django_logit-1.1.4.dist-info/RECORD
