Metadata-Version: 2.1
Name: django-logit
Version: 1.1.4
Summary: Django Decorator of Logging Request Params/Response Content
Home-page: https://github.com/Brightcells/django-logit
Author: Hackathon
Author-email: kimi.huang@brightcells.com
Keywords: Django Logging Log POST GET Query Params
Classifier: Development Status :: 5 - Production/Stable
Classifier: Environment :: Web Environment
Classifier: Framework :: Django
Classifier: Intended Audience :: Developers
Classifier: Programming Language :: Python
Classifier: Topic :: Software Development :: Libraries :: Python Modules
Classifier: Topic :: Office/Business :: Financial :: Spreadsheet
